garpix_blog/MANIFEST.in
garpix_blog/__init__.py
garpix_blog/apps.py
garpix_blog/setup.py
garpix_blog/tests.py
garpix_blog/urls.py
garpix_blog/__pycache__/__init__.cpython-38.pyc
garpix_blog/__pycache__/apps.cpython-38.pyc
garpix_blog/admin/__init__.py
garpix_blog/admin/blog.py
garpix_blog/admin/category_page.py
garpix_blog/admin/post.py
garpix_blog/admin/post_image.py
garpix_blog/admin/post_video.py
garpix_blog/admin/__pycache__/__init__.cpython-38.pyc
garpix_blog/admin/__pycache__/blog.cpython-38.pyc
garpix_blog/admin/__pycache__/category_page.cpython-38.pyc
garpix_blog/admin/__pycache__/post.cpython-38.pyc
garpix_blog/admin/__pycache__/post_image.cpython-38.pyc
garpix_blog/admin/__pycache__/post_video.cpython-38.pyc
garpix_blog/managers/__init__.py
garpix_blog/managers/__pycache__/__init__.cpython-38.pyc
garpix_blog/managers/polymorphic_active_manager/__init__.py
garpix_blog/managers/polymorphic_active_manager/polymorphic_active_manager.py
garpix_blog/managers/polymorphic_active_manager/__pycache__/__init__.cpython-38.pyc
garpix_blog/managers/polymorphic_active_manager/__pycache__/polymorphic_active_manager.cpython-38.pyc
garpix_blog/mixins/__init__.py
garpix_blog/mixins/empty_mixin.py
garpix_blog/mixins/polymorphic_active_mixin.py
garpix_blog/mixins/__pycache__/__init__.cpython-38.pyc
garpix_blog/mixins/__pycache__/empty_mixin.cpython-38.pyc
garpix_blog/mixins/__pycache__/polymorphic_active_mixin.cpython-38.pyc
garpix_blog/models/__init__.py
garpix_blog/models/blog.py
garpix_blog/models/category_page.py
garpix_blog/models/post.py
garpix_blog/models/post_image.py
garpix_blog/models/post_video.py
garpix_blog/models/__pycache__/__init__.cpython-38.pyc
garpix_blog/models/__pycache__/blog.cpython-38.pyc
garpix_blog/models/__pycache__/category_page.cpython-38.pyc
garpix_blog/models/__pycache__/post.cpython-38.pyc
garpix_blog/models/__pycache__/post_image.cpython-38.pyc
garpix_blog/models/__pycache__/post_video.cpython-38.pyc
garpix_blog/serializers/__init__.py
garpix_blog-1.1.0.dist-info/METADATA
garpix_blog-1.1.0.dist-info/WHEEL
garpix_blog-1.1.0.dist-info/top_level.txt
garpix_blog-1.1.0.dist-info/RECORD
